{
  "categories": [
    {
      "id": "bracelets",
      "name": "Bracelets",
      "description": "Handpicked bracelet designs."
    },
    {
      "id": "rings",
      "name": "Rings",
      "description": "Stylish rings collection."
    },
    {
      "id": "earrings",
      "name": "Earrings",
      "description": "Elegant earrings."
    },
    {
      "id": "necklaces",
      "name": "Necklaces",
      "description": "Pharohs Necklace designed to make you feel the vibes of our culture"
    },
    {
      "id": "silver",
      "name": "Silver",
      "description": ""
    },
    {
      "id": "watch",
      "name": "Watch",
      "description": ""
    },
    {
      "id": "ring",
      "name": "Ring",
      "description": "",
      "section": "stainless"
    }
  ],
  "products": [
    {
      "id": "hh_1759446432107",
      "title": "hh",
      "price": 3000,
      "category": "bracelets",
      "images": [
        "uploads/bracelets/1759446432100_Pharos_Necklace_-_Copy.jpg"
      ],
      "desc": ""
    }
  ],
  "removedProducts": [],
  "removedCategories": []
}